README.md
setup.py
cnn_visualiser/__init__.py
cnn_visualiser/grad_cam.py
cnn_visualiser/gradient_visualiser.py
cnn_visualiser/integrated_gradients.py
cnn_visualiser/intermediate_activations.py
cnn_visualiser/vanilla_gradients.py
conv_visualiser.egg-info/PKG-INFO
conv_visualiser.egg-info/SOURCES.txt
conv_visualiser.egg-info/dependency_links.txt
conv_visualiser.egg-info/not-zip-safe
conv_visualiser.egg-info/top_level.txt