Metadata-Version: 1.0
Name: conv-visualiser
Version: 0.4
Summary: Functions to visualize intermediate activations and features of a CNN
Home-page: UNKNOWN
Author: UNKNOWN
Author-email: UNKNOWN
License: UNKNOWN
Platform: UNKNOWN
